[
    {
        "id": 1,
        "title": "",
        "image": "images/post.png",
        "description": "Some quick example text to build on the card title and make up the bulk of the card's content."
    },
    {
        "id": 2,
        "title": "",
        "image": "images/post.png",
        "description": "Some quick example text to build on the card title and make up the bulk of the card's content."
    },
    {
        "id": 3,
        "title": "",
        "image": "images/post.png",
        "description": "Some quick example text to build on the card title and make up the bulk of the card's content."
    },
    {
        "id": 4,
        "title": "",
        "image": "images/post.png",
        "description": "Some quick example text to build on the card title and make up the bulk of the card's content."
    },
    {
        "id": 5,
        "title": "",
        "image": "images/post.png",
        "description": "Some quick example text to build on the card title and make up the bulk of the card's content."
    },
    {
        "id": 6,
        "title": "",
        "image": "images/post.png",
        "description": "Some quick example text to build on the card title and make up the bulk of the card's content."
    },
    {
        "id": 7,
        "title": "",
        "image": "images/post.png",
        "description": "Some quick example text to build on the card title and make up the bulk of the card's content."
    },
    {
        "id": 8,
        "title": "",
        "image": "images/post.png",
        "description": "Some quick example text to build on the card title and make up the bulk of the card's content."
    },
    {
        "id": 9,
        "title": "",
        "image": "images/post.png",
        "description": "Some quick example text to build on the card title and make up the bulk of the card's content."
    },
    {
        "id": 10,
        "title": "",
        "image": "images/post.png",
        "description": "Some quick example text to build on the card title and make up the bulk of the card's content."
    }
]
